ucm/Dialogs.py
ucm/DockerListView.py
ucm/Registry.py
ucm/SshListView.py
ucm/SwarmListView.py
ucm/TabGroup.py
ucm/UserConfig.py
ucm/Widgets.py
ucm/__init__.py
ucm/constants.py
ucm/help.txt
ucm/ucm-swarmlisting.sh
ucm-0.1.2.data/scripts/ucm
ucm-0.1.2.dist-info/LICENSE
ucm-0.1.2.dist-info/METADATA
ucm-0.1.2.dist-info/WHEEL
ucm-0.1.2.dist-info/top_level.txt
ucm-0.1.2.dist-info/RECORD
