Metadata-Version: 2.1
Name: ucm
Version: 0.1.2
Summary: Urwid rendered Connection Manager
Home-page: https://github.com/rszabo50/ucm
Author: Robert Szabo
Author-email: rszabo50@gmail.com
License: UNKNOWN
Project-URL: Bug Tracker, https://github.com/rszabo50/ucm/issues
Platform: UNKNOWN
Classifier: Natural Language :: English
Classifier: Programming Language :: Python :: 3
Classifier: Programming Language :: Python :: 3.0
Classifier: Programming Language :: Python :: 3.1
Classifier: Programming Language :: Python :: 3.2
Classifier: Programming Language :: Python :: 3.3
Classifier: Programming Language :: Python :: 3.4
Classifier: Programming Language :: Python :: 3.5
Classifier: Programming Language :: Python :: 3.6
Classifier: Programming Language :: Python :: 3.7
Classifier: Programming Language :: Python :: 3.8
Classifier: Programming Language :: Python :: 3.9
Classifier: Programming Language :: Python :: 3.10
Classifier: Programming Language :: Python :: 3.11
Classifier: Programming Language :: Python :: Implementation
Classifier: Programming Language :: Python :: Implementation :: PyPy
Classifier: License :: OSI Approved :: GNU General Public License v3 (GPLv3)
Classifier: Intended Audience :: Developers
Classifier: Intended Audience :: System Administrators
Classifier: Development Status :: 5 - Production/Stable
Classifier: Operating System :: MacOS :: MacOS X
Classifier: Operating System :: OS Independent
Classifier: Operating System :: POSIX
Classifier: Operating System :: POSIX :: AIX
Classifier: Operating System :: POSIX :: BSD
Classifier: Operating System :: POSIX :: BSD :: BSD/OS
Classifier: Operating System :: POSIX :: BSD :: FreeBSD
Classifier: Operating System :: POSIX :: BSD :: NetBSD
Classifier: Operating System :: POSIX :: BSD :: OpenBSD
Classifier: Operating System :: POSIX :: GNU Hurd
Classifier: Operating System :: POSIX :: HP-UX
Classifier: Operating System :: POSIX :: IRIX
Classifier: Operating System :: POSIX :: Linux
Classifier: Operating System :: POSIX :: Other
Classifier: Operating System :: POSIX :: SCO
Classifier: Operating System :: POSIX :: SunOS/Solaris
Classifier: Operating System :: Unix
Classifier: Topic :: System :: Systems Administration
Classifier: Topic :: Utilities
Requires-Python: >=3.6
License-File: LICENSE
Requires-Dist: PyYAML
Requires-Dist: urwid
Requires-Dist: panwid
Requires-Dist: datatables
Requires-Dist: dataclasses
